{
  "1": {
    "roles": 80,
    "images": 408,
    "size": 2574422988,
    "gitSize": 1920861858,
    "filesSize": 653561130,
    "lastUpdate": "2025-08-21 15:50",
    "sha": "9543c3e68c07129271c9",
    "nodeName": "GitHub"
  },
  "2": {
    "roles": 95,
    "images": 861,
    "size": 1889098972,
    "gitSize": 1141379668,
    "filesSize": 747719304,
    "lastUpdate": "2025-08-21 16:21",
    "sha": "2144e2c04e6b545eea00",
    "nodeName": "GitHub"
  },
  "3": {
    "roles": 56,
    "images": 462,
    "size": 1045761987,
    "gitSize": 579162543,
    "filesSize": 466599444,
    "lastUpdate": "2025-08-07 14:17",
    "sha": "65386da979dc561b31fa",
    "nodeName": "GitHub"
  },
  "4": {
    "roles": 0,
    "images": 0,
    "size": 0,
    "gitSize": 0,
    "filesSize": 0,
    "lastUpdate": "N/A",
    "sha": "获取失败",
    "nodeName": "未知"
  },
  "lastUpdated": "2025-08-21T10:58:44.293Z"
}